cracker/__init__.py
cracker/cracker.py
cracker/cracker_gui.py
cracker/icon.jpeg
cracker/icon.png
cracker/keylogger.py
cracker/main.py
cracker/mp3_helper.py
cracker/ssml.py
cracker/text_parser.py
cracker/themes.py
cracker/utils.py
cracker/config/__init__.py
cracker/config/configuration.py
cracker/config/default.yaml
cracker/config/parser.json
cracker/speaker/__init__.py
cracker/speaker/abstract_speaker.py
cracker/speaker/espeak.py
cracker/speaker/frogger.py
cracker/speaker/google.py
cracker/speaker/polly.py
cracker/tests/test_config.py
cracker/tests/test_text_parser.py
cracker/view/__init__.py
cracker/view/config_window.py
cracker/view/parser_config_tab.py
cracker/view/speaker_config_tab.py
cracker-0.9.0.dist-info/licenses/LICENSE
cracker-0.9.0.dist-info/METADATA
cracker-0.9.0.dist-info/WHEEL
cracker-0.9.0.dist-info/entry_points.txt
cracker-0.9.0.dist-info/top_level.txt
cracker-0.9.0.dist-info/RECORD
