Metadata-Version: 2.4
Name: cracker
Version: 0.9.0
Requires-Python: >=3.10
License-File: LICENSE
Requires-Dist: boto3==1.26.*
Requires-Dist: python-vlc==3.*
Requires-Dist: pyqt5==5.15.*
Requires-Dist: pynput==1.7.*
Requires-Dist: pyttsx3==2.90.*
Requires-Dist: google-cloud-texttospeech==2.5.*
Requires-Dist: darkdetect==0.8.*
Requires-Dist: pyyaml
Requires-Dist: setuptools>=80.9.0
Provides-Extra: dev
Requires-Dist: black==23.1.*; extra == "dev"
Requires-Dist: isort==5.12.*; extra == "dev"
Requires-Dist: pycodestyle; extra == "dev"
Provides-Extra: build
Requires-Dist: setuptools>=61; extra == "build"
Requires-Dist: build; extra == "build"
Requires-Dist: twine; extra == "build"
Provides-Extra: test
Requires-Dist: pytest; extra == "test"
Dynamic: license-file
